pixar_render/__init__.py
pixar_render/pangocairo_render.py
pixar_render/processor.py
pixar_render/resources/environment.yml
pixar_render/resources/render_default_conf.json
pixar_render/resources/fonts/GoNotoCurrent.ttf
pixar_render/resources/fonts/PixeloidSans-mLxMm.ttf
pixar_render-0.1.3.dist-info/licenses/LICENSE
pixar_render-0.1.3.dist-info/METADATA
pixar_render-0.1.3.dist-info/WHEEL
pixar_render-0.1.3.dist-info/top_level.txt
pixar_render-0.1.3.dist-info/RECORD
