Metadata-Version: 2.4
Name: Pixar-Render
Version: 0.1.3
Summary: Provide rendering functions for project PIXAR.
Author: Yintao Tai
Author-email: Yintao Tai <tai.yintao@gmail.com>
License:                                  Apache License
Project-URL: Homepage, https://github.com/TYTTYTTYT/Pixar-Render
Project-URL: Bug Tracker, https://github.com/TYTTYTTYT/Pixar-Render/issues
Project-URL: repository, https://github.com/TYTTYTTYT/Pixar-Render.git
Classifier: Programming Language :: Python :: 3
Classifier: License :: OSI Approved :: Apache Software License
Classifier: Operating System :: OS Independent
Classifier: Topic :: Scientific/Engineering :: Artificial Intelligence
Classifier: Topic :: Utilities
Classifier: Topic :: Software Development :: Libraries :: Python Modules
Classifier: Development Status :: 2 - Pre-Alpha
Classifier: Intended Audience :: Developers
Classifier: Intended Audience :: Education
Classifier: Intended Audience :: Information Technology
Classifier: Intended Audience :: Science/Research
Classifier: Typing :: Typed
Requires-Python: ==3.11.*
License-File: LICENSE
Requires-Dist: numpy
Requires-Dist: torch
Requires-Dist: torchvision
Requires-Dist: pillow
Dynamic: author
Dynamic: license-file
Dynamic: requires-python
